__init__.py
endlessdb.py
endlessdb-0.4.15.dist-info/LICENSE.txt
endlessdb-0.4.15.dist-info/METADATA
endlessdb-0.4.15.dist-info/WHEEL
endlessdb-0.4.15.dist-info/top_level.txt
endlessdb-0.4.15.dist-info/RECORD
