Metadata-Version: 2.1
Name: endlessdb
Version: 0.4.15
Summary: Endless Database with pyyaml and pymongo
Author-email: Andrew Berlin <a.berlin@33solutions.company>
Maintainer-email: Andrew Berlin <a.berlin@33solutions.company>
License: Apache License
Project-URL: repository, https://github.com
Project-URL: homepage, https://github.com/33solutions/endlessdb
Project-URL: issues, https://github.com/33solutions/endlessdb/issues
Project-URL: changelog, https://github.com/33solutions/endlessdb/blob/master/CHANGELOG.md
Classifier: Development Status :: 4 - Beta
Classifier: Programming Language :: Python :: 3
Classifier: License :: OSI Approved :: Apache Software License
Classifier: Operating System :: OS Independent
Requires-Python: >=3.8
License-File: LICENSE.txt
Requires-Dist: pymongo >=4.7.2
Requires-Dist: pyyaml >=6.0.1
